lemutils/__init__.py
lemutils/chat_formatting.py
lemutils/checks.py
lemutils/converters.py
lemutils/dataIO.py
lemutils/settings.py
lemutils-1.1.dist-info/LICENSE
lemutils-1.1.dist-info/METADATA
lemutils-1.1.dist-info/WHEEL
lemutils-1.1.dist-info/top_level.txt
lemutils-1.1.dist-info/RECORD
