Metadata-Version: 2.1
Name: lemutils
Version: 1.1
Summary: utils for yeetbot
Home-page: https://github.com/blankLeM/lemutils
Author: notlem
Author-email: datjboy@gmail.com
License: UNKNOWN
Platform: UNKNOWN
Classifier: Programming Language :: Python :: 3.5
Classifier: Operating System :: OS Independent
